setup.py
snowwhite/__init__.py
snowwhite/discourse_mapper.py
snowwhite/english_stoplist.py
snowwhite/explicit_sentiment.py
snowwhite/linguist.py
snowwhite/sentiment_demo.py
snowwhite/spanish_stoplist.py
snowwhite/text_sentiment.py
snowwhite/utils.py
snowwhite/wordbag.py
snowwhite.egg-info/PKG-INFO
snowwhite.egg-info/SOURCES.txt
snowwhite.egg-info/dependency_links.txt
snowwhite.egg-info/requires.txt
snowwhite.egg-info/top_level.txt
snowwhite/data/__init__.py