Metadata-Version: 1.0
Name: snowwhite
Version: 0.1.1
Summary: An implicit and explicit sentiment analyzer.
Home-page: UNKNOWN
Author: Maksim Tsvetovat, @maksim2042
Author-email: maksim@tsvetovat.org
License: UNKNOWN
Platform: UNKNOWN
